astate/__init__.py
astate/misc.py
astate/util.py
astate-0.0.7.dist-info/LICENSE
astate-0.0.7.dist-info/METADATA
astate-0.0.7.dist-info/WHEEL
astate-0.0.7.dist-info/top_level.txt
astate-0.0.7.dist-info/RECORD
