Metadata-Version: 2.1
Name: astate
Version: 0.0.7
Summary: Various AST utils
Home-page: https://github.com/thorwhalen/astate
Author: Thor Whalen
License: apache-2.0
Platform: any
License-File: LICENSE
